file_parser_package/__init__.py
file_parser_package/file_parser.py
file_parser_kingish-0.0.1.dist-info/METADATA
file_parser_kingish-0.0.1.dist-info/WHEEL
file_parser_kingish-0.0.1.dist-info/entry_points.txt
file_parser_kingish-0.0.1.dist-info/top_level.txt
file_parser_kingish-0.0.1.dist-info/RECORD
